{"data":{"site":{"siteMetadata":{"projects":[{"title":"Public Notes","description":"Watch what I'm currently learning, and other references I aggregate over time.","details":"brettinternet/public-notes","href":"https://github.com/brettinternet/public-notes"},{"title":"Dotfiles","description":"My .files, configs and setup. I love improving my Unix environment.","details":"brettinternet/dotfiles","href":"https://github.com/brettinternet/dotfiles"},{"title":"CV","description":"I wrote my CV with LaTeX, if you're an employer, check it out!","details":"brettinternet/cv","href":"#"},{"title":"This blog! 😎","description":"this is my resume","details":"brettinternet/brettinternet.github.io","href":"#"}]}}},"pageContext":{"isCreatedByStatefulCreatePages":true}}